bloggertool/remote.py
bloggertool/encoding.py
bloggertool/main.py
bloggertool/notify.py
bloggertool/__init__.py
bloggertool/str_util.py
bloggertool/ui.py
bloggertool/__version__.py
bloggertool/exceptions.py
bloggertool/log_util.py
bloggertool/engine/markdown.py
bloggertool/engine/__init__.py
bloggertool/engine/rest.py
bloggertool/help/template.py
bloggertool/help/__init__.py
bloggertool/help/help.py
bloggertool/config/config.py
bloggertool/config/post.py
bloggertool/config/info.py
bloggertool/config/__init__.py
bloggertool/config/attrs.py
bloggertool/config/file_system.py
bloggertool/commands/rm.py
bloggertool/commands/browse.py
bloggertool/commands/diff.py
bloggertool/commands/rinfo.py
bloggertool/commands/ls.py
bloggertool/commands/publish.py
bloggertool/commands/show.py
bloggertool/commands/basecommand.py
bloggertool/commands/link.py
bloggertool/commands/info.py
bloggertool/commands/label.py
bloggertool/commands/__init__.py
bloggertool/commands/html.py
bloggertool/commands/init.py
bloggertool/commands/push.py
bloggertool/commands/rls.py
bloggertool/commands/add.py
bloggertool-0.4.2.dist-info/entry_points.txt
bloggertool-0.4.2.dist-info/DESCRIPTION.rst
bloggertool-0.4.2.dist-info/top_level.txt
bloggertool-0.4.2.dist-info/zip-safe
bloggertool-0.4.2.dist-info/metadata.json
bloggertool-0.4.2.dist-info/WHEEL
bloggertool-0.4.2.dist-info/RECORD
bloggertool-0.4.2.dist-info/METADATA
