Metadata-Version: 2.0
Name: bloggertool
Version: 0.4.2
Summary: Command line tool to communicate with blogger.com and blogspot.com.
Home-page: https://github.com/asvetlov/bloggertool
Author: Andrew Svetlov
Author-email: andrew.svetlov@gmail.com
License: MIT
Platform: UNKNOWN
Classifier: Development Status :: 3 - Alpha
Classifier: Environment :: Console
Classifier: Intended Audience :: End Users/Desktop
Classifier: License :: OSI Approved :: MIT License
Classifier: Natural Language :: English
Classifier: Operating System :: OS Independent
Classifier: Programming Language :: Python :: 2.7
Classifier: Topic :: Internet
Requires-Dist: python-dateutil
Requires-Dist: keyring
Requires-Dist: jinja2
Requires-Dist: markdown
Requires-Dist: PyYAML
Requires-Dist: pyinotify
Requires-Dist: googleapiclient
Requires-Dist: transliterate
